{
    "DNDConfig": null,
    "_height_": {
        "type": "string",
        "value": "100dp"
    },
    "_left_": {
        "type": "string",
        "value": "30dp"
    },
    "_margin_": [
        0,
        0,
        0,
        0
    ],
    "_orientation_": 6,
    "_padding_": [
        0,
        0,
        0,
        0
    ],
    "_percent_": true,
    "_skin_": "sfc853bdd0874876b56b9104246e8d79",
    "_top_": {
        "type": "string",
        "value": "30dp"
    },
    "_width_": {
        "type": "string",
        "value": "75%"
    },
    "allboxes": [],
    "autogrowmode": 0,
    "canUpdateUI": true,
    "centerx": {
        "type": "string",
        "value": "50%"
    },
    "children": [
        "listTitle"
    ],
    "clipbounds": true,
    "containerweight": 100,
    "enablescrolling": true,
    "id": "listTitleContainer",
    "info": null,
    "iscustomlayout": false,
    "isvisible": true,
    "kuid": "f09885b0b675408589f434f0036d2274",
    "layouttype": 2,
    "name": "kony.ui.FlexContainer",
    "parent": "listProductsContainer",
    "pf": "listProducts",
    "retaincontentalignment": false,
    "retainflexpositionproperties": false,
    "retainflowhorizontalalignment": false,
    "snapgridsize": 10,
    "snaptogrid": true,
    "wType": "FlexContainer",
    "widgetalignment": 1,
    "zindex": 1
}