{
    "DNDConfig": null,
    "_height_": {
        "type": "string",
        "value": "100%"
    },
    "_left_": {
        "type": "string",
        "value": "0dp"
    },
    "_margin_": [
        0,
        0,
        0,
        0
    ],
    "_orientation_": 6,
    "_padding_": [
        0,
        0,
        0,
        0
    ],
    "_percent_": true,
    "_skin_": "s9dcb81d20644b91b6b633135461f2f0",
    "_top_": {
        "type": "string",
        "value": "0dp"
    },
    "_width_": {
        "type": "string",
        "value": "100%"
    },
    "allboxes": [],
    "autogrowmode": 0,
    "canUpdateUI": true,
    "children": [
        "lblStockAvailable",
        "lblStock"
    ],
    "clipbounds": true,
    "containerweight": 100,
    "enablescrolling": true,
    "id": "stockContainer",
    "info": null,
    "iscustomlayout": false,
    "isvisible": true,
    "kuid": "i83cb5105acf485b9fd739db3448fe4e",
    "layouttype": 4,
    "name": "kony.ui.FlexContainer",
    "parent": "row2Container",
    "pf": "listProducts",
    "responsiveconfig": {
        "offset": {
            "b1": 0,
            "b2": 0,
            "b3": 0
        },
        "span": {
            "b1": 6,
            "b2": 4,
            "b3": 6
        }
    },
    "retaincontentalignment": false,
    "retainflexpositionproperties": false,
    "retainflowhorizontalalignment": false,
    "snapgridsize": 10,
    "snaptogrid": true,
    "wType": "FlexContainer",
    "widgetalignment": 1,
    "zindex": 1
}